backtest/__init__.py
backtest/app.py
backtest/cli.py
backtest/common/__init__.py
backtest/common/helper.py
backtest/config/__init__.py
backtest/config/defaults.yaml
backtest/config/dev.yaml
backtest/config/schema.py
backtest/feed/__init__.py
backtest/feed/basefeed.py
backtest/feed/zillionarefeed.py
backtest/trade/__init__.py
backtest/trade/broker.py
backtest/trade/datatypes.py
backtest/trade/trade.py
backtest/trade/transaction.py
backtest/web/__init__.py
backtest/web/accounts.py
backtest/web/interfaces.py
tests/__init__.py
tests/common/__init__.py
tests/common/test_helper.py
tests/data/bars_1d.pkl
tests/data/bars_1m.pkl
tests/data/hljh_1d.csv
tests/data/hljh_1m.csv
tests/data/issue36.pkl
tests/data/limits.csv
tests/data/readme.md
tests/data/tyst_1d.csv
tests/data/tyst_1m.csv
tests/data/validation.xlsx
tests/feed/__init__.py
tests/feed/test_zillionarefeed.py
tests/test_app.py
tests/test_cli.py
tests/trade/__init__.py
tests/trade/test_broker.py
tests/web/__init__.py
tests/web/test_interfaces.py
zillionare_backtest-0.5.0.dist-info/LICENSE
zillionare_backtest-0.5.0.dist-info/METADATA
zillionare_backtest-0.5.0.dist-info/WHEEL
zillionare_backtest-0.5.0.dist-info/entry_points.txt
zillionare_backtest-0.5.0.dist-info/RECORD
