Metadata-Version: 2.1
Name: zillionare-backtest
Version: 0.5.0
Summary: zillionare backtest framework.
Home-page: https://github.com/zillionare/backtest
License: MIT
Author: Aaron Yang
Author-email: aaron_yang@jieyu.ai
Requires-Python: >=3.8,<3.9
Classifier: Development Status :: 2 - Pre-Alpha
Classifier: Intended Audience :: Developers
Classifier: License :: OSI Approved :: MIT License
Classifier: Natural Language :: English
Classifier: Programming Language :: Python :: 3
Classifier: Programming Language :: Python :: 3.8
Classifier: Programming Language :: Python :: 3.8
Provides-Extra: dev
Provides-Extra: doc
Provides-Extra: test
Requires-Dist: Jinja2 (>=3.0,<3.1) ; extra == "doc"
Requires-Dist: aioredis (>=2.0,<3.0)
Requires-Dist: async-timeout (>=4.0,<5.0)
Requires-Dist: black (>=22.3.0,<23.0.0) ; extra == "dev"
Requires-Dist: cfg4py (>=0.9.4,<0.10.0)
Requires-Dist: expiringdict (>=1.2.1,<2.0.0)
Requires-Dist: fire (==0.4.0)
Requires-Dist: flake8 (==4.0.1) ; extra == "dev"
Requires-Dist: flake8-docstrings (>=1.6.0,<2.0.0) ; extra == "dev"
Requires-Dist: isort (==5.10.1) ; extra == "dev"
Requires-Dist: livereload (>=2.6.3,<3.0.0) ; extra == "doc"
Requires-Dist: mike (>=1.1.2,<2.0.0) ; extra == "doc"
Requires-Dist: mkdocs (>=1.2.3,<2.0.0) ; extra == "doc"
Requires-Dist: mkdocs-autorefs (>=0.4.1,<0.5.0) ; extra == "doc"
Requires-Dist: mkdocs-include-markdown-plugin (>=3.2.3,<4.0.0) ; extra == "doc"
Requires-Dist: mkdocs-material (>=8.1.11,<9.0.0) ; extra == "doc"
Requires-Dist: mkdocs-material-extensions (>=1.0.3,<2.0.0)
Requires-Dist: mkdocstrings (>=0.18.0,<0.19.0) ; extra == "doc"
Requires-Dist: pandas (>=1.4.1,<2.0.0)
Requires-Dist: pre-commit (>=2.17.0,<3.0.0) ; extra == "dev"
Requires-Dist: psutil (>=5.9.0,<6.0.0)
Requires-Dist: pyemit (>=0.5.0,<0.6.0)
Requires-Dist: pyreadline (>=2.1,<3.0)
Requires-Dist: pytest (>=7.0.1,<8.0.0) ; extra == "test"
Requires-Dist: pytest-cov (>=3.0.0,<4.0.0) ; extra == "test"
Requires-Dist: sanic (>=21.12.1,<22.0.0)
Requires-Dist: sanic-testing (>=0.8.2,<0.9.0) ; extra == "test"
Requires-Dist: tabulate (>=0.8.9,<0.9.0)
Requires-Dist: toml (>=0.10.2,<0.11.0) ; extra == "dev"
Requires-Dist: tox (>=3.24.5,<4.0.0) ; extra == "dev"
Requires-Dist: tqdm (>=4.63.0,<5.0.0)
Requires-Dist: twine (>=3.8.0,<4.0.0) ; extra == "dev"
Requires-Dist: virtualenv (>=20.13.1,<21.0.0) ; extra == "dev"
Requires-Dist: websockets (<11.0)
Requires-Dist: zillionare-core-types (>=0.6.2,<0.7.0)
Requires-Dist: zillionare-omicron (>=2.0.0a76,<3.0.0)
